pytest_snap/__init__.py
pytest_snap/plugin.py
pytest_snap/py.typed
pytest_snap/round.py
pytest_snap-0.2.1.dist-info/licenses/LICENSE
pytest_snap-0.2.1.dist-info/WHEEL
pytest_snap-0.2.1.dist-info/entry_points.txt
pytest_snap-0.2.1.dist-info/METADATA
pytest_snap-0.2.1.dist-info/RECORD
