Metadata-Version: 2.4
Name: pytest-snap
Version: 0.2.1
Summary: A text-based snapshot testing library implemented as a pytest plugin
Keywords: pytest-plugin,pytest,testing,snapshot,snapshot-testing
Author: Mario Theers
Author-email: Mario Theers <mario.theers@gmail.com>
License-Expression: MIT
License-File: LICENSE
Classifier: Framework :: Pytest
Requires-Dist: pytest>=8.0.0
Requires-Python: >=3.10
Project-URL: Homepage, https://github.com/thomasfermi/pytest-snap
Project-URL: Issues, https://github.com/thomasfermi/pytest-snap/issues
